shopcloud_django_instrumenting/__init__.py
shopcloud_django_instrumenting/middleware.py
shopcloud_django_instrumenting/tracing.py
shopcloud_django_instrumenting-1.4.0.dist-info/LICENSE
shopcloud_django_instrumenting-1.4.0.dist-info/METADATA
shopcloud_django_instrumenting-1.4.0.dist-info/WHEEL
shopcloud_django_instrumenting-1.4.0.dist-info/top_level.txt
shopcloud_django_instrumenting-1.4.0.dist-info/RECORD
