Metadata-Version: 2.1
Name: shopcloud-django-instrumenting
Version: 1.4.0
Summary: Django tool for instrumenting
Home-page: https://github.com/Talk-Point/shopcloud-django-instrumenting
Author: Konstantin Stoldt
Author-email: konstantin.stoldt@talk-point.de
License: MIT
License-File: LICENSE
Requires-Dist: Django <6.0,>=3.2
Requires-Dist: djangorestframework
